pypodo/__init__.py
pypodo/add.py
pypodo/args.py
pypodo/backup.py
pypodo/check.py
pypodo/config.py
pypodo/delete.py
pypodo/list.py
pypodo/print.py
pypodo/properties.py
pypodo/search.py
pypodo/sort.py
pypodo/tag.py
pypodo/untag.py
pypodo/update.py
pypodo/version.py
pypodo-5.3.3.dist-info/LICENSE.txt
pypodo-5.3.3.dist-info/METADATA
pypodo-5.3.3.dist-info/WHEEL
pypodo-5.3.3.dist-info/entry_points.txt
pypodo-5.3.3.dist-info/top_level.txt
pypodo-5.3.3.dist-info/RECORD
